scripts/__init__.py
scripts/upload.py
sentinelc_appfeed/__init__.py
sentinelc_appfeed/builder.py
sentinelc_appfeed/validator.py
sentinelc_appfeed/utils/ArgparseCustomTypes.py
sentinelc_appfeed/utils/__init__.py
sentinelc_appfeed/utils/exceptions.py
sentinelc_appfeed/utils/jinja.py
sentinelc_appfeed/utils/logger.py
sentinelc_appfeed/utils/safe_yaml.py
sentinelc_appfeed/utils/utils.py
sentinelc_appfeed-6.0.2.dist-info/LICENSE.txt
sentinelc_appfeed-6.0.2.dist-info/METADATA
sentinelc_appfeed-6.0.2.dist-info/WHEEL
sentinelc_appfeed-6.0.2.dist-info/entry_points.txt
sentinelc_appfeed-6.0.2.dist-info/top_level.txt
sentinelc_appfeed-6.0.2.dist-info/RECORD
