Metadata-Version: 2.1
Name: sentinelc-appfeed
Version: 6.0.2
Summary: Tools used to validate, create and publish an app libary feed for the SentinelC platform.
Home-page: https://gitlab.com/sentinelc/app-library-builder
Maintainer: SentinelC
License-File: LICENSE.txt
Requires-Dist: PyYAML
Requires-Dist: humanfriendly
Requires-Dist: jinja2
